stdchecker/__init__.py
stdchecker/astm.py
stdchecker/constants.py
stdchecker/iec.py
stdchecker/ieee.py
stdchecker/tse.py
stdchecker-0.1.6.dist-info/LICENSE
stdchecker-0.1.6.dist-info/METADATA
stdchecker-0.1.6.dist-info/WHEEL
stdchecker-0.1.6.dist-info/top_level.txt
stdchecker-0.1.6.dist-info/RECORD
