Metadata-Version: 2.1
Name: stdchecker
Version: 0.1.6
Summary: A library for checking the latest revisions of standard methods published by standard bodies.
Home-page: https://github.com/emreture/stdchecker
Author: Metin Emre TÜRE
Author-email: emreture@gmail.com
License: MIT
Platform: UNKNOWN
Classifier: Development Status :: 5 - Production/Stable
Classifier: License :: OSI Approved :: MIT License
Classifier: Programming Language :: Python :: 3.8
Classifier: Operating System :: OS Independent
Classifier: Intended Audience :: Science/Research
Classifier: Natural Language :: English
Requires-Python: >=3.8
License-File: LICENSE
Requires-Dist: beautifulsoup4
Requires-Dist: requests
